odoo/addons/web_notify_upgrade/README.rst
odoo/addons/web_notify_upgrade/__init__.py
odoo/addons/web_notify_upgrade/__manifest__.py
odoo/addons/web_notify_upgrade/i18n/web_notify_upgrade.pot
odoo/addons/web_notify_upgrade/models/__init__.py
odoo/addons/web_notify_upgrade/models/ir_model.py
odoo/addons/web_notify_upgrade/readme/CONTRIBUTORS.rst
odoo/addons/web_notify_upgrade/readme/DESCRIPTION.rst
odoo/addons/web_notify_upgrade/static/description/icon.png
odoo/addons/web_notify_upgrade/static/description/index.html
odoo14_addon_web_notify_upgrade-14.0.1.0.1.dist-info/METADATA
odoo14_addon_web_notify_upgrade-14.0.1.0.1.dist-info/WHEEL
odoo14_addon_web_notify_upgrade-14.0.1.0.1.dist-info/top_level.txt
odoo14_addon_web_notify_upgrade-14.0.1.0.1.dist-info/RECORD
